{
    "os": "Linux-5.4.0-162-generic-x86_64-with-glibc2.31",
    "python": "3.10.0",
    "heartbeatAt": "2024-04-02T20:29:31.742170",
    "startedAt": "2024-04-02T20:29:31.259511",
    "docker": null,
    "cuda": null,
    "args": [
        "typo.beta=0.0",
        "wandb.name=typo-lr-5e-7-iteration-1",
        "training.checkpoint_dir=/scr/jphilipp/typo/trained_models/Mistral-7B-v0.1/hh-rlhf-fixed/typo-5e-7-iteration-1",
        "training.lr=5e-7",
        "data_path=data/base",
        "helpful=helpful.json",
        "harmless=harmless.json",
        "n_examples=2000"
    ],
    "state": "running",
    "program": "/sailhome/jphilipp/research_projects/typo/experiments/hh-rlhf/train_typo.py",
    "codePathLocal": "train_typo.py",
    "codePath": "experiments/hh-rlhf/train_typo.py",
    "git": {
        "remote": "git@github.com:janphilippfranken/scai-tuning.git",
        "commit": "17ac80c18523930c4331e8a5bd9a6cdbb13922aa"
    },
    "email": "janphilipp.franken@gmail.com",
    "root": "/sailhome/jphilipp/research_projects/typo",
    "host": "cocoflops-hgx-1",
    "username": "jphilipp",
    "executable": "/scr/jphilipp/miniconda3/envs/typo/bin/python",
    "cpu_count": 64,
    "cpu_count_logical": 128,
    "cpu_freq": {
        "current": 1849.4525781249997,
        "min": 1500.0,
        "max": 2800.0
    },
    "cpu_freq_per_core": [
        {
            "current": 1561.515,
            "min": 1500.0,
            "max": 2800.0
        },
        {
            "current": 1542.366,
            "min": 1500.0,
            "max": 2800.0
        },
        {
            "current": 1533.374,
            "min": 1500.0,
            "max": 2800.0
        },
        {
            "current": 1615.278,
            "min": 1500.0,
            "max": 2800.0
        },
        {
            "current": 1495.986,
            "min": 1500.0,
            "max": 2800.0
        },
        {
            "current": 1492.157,
            "min": 1500.0,
            "max": 2800.0
        },
        {
            "current": 1491.082,
            "min": 1500.0,
            "max": 2800.0
        },
        {
            "current": 1496.798,
            "min": 1500.0,
            "max": 2800.0
        },
        {
            "current": 1720.758,
            "min": 1500.0,
            "max": 2800.0
        },
        {
            "current": 1572.78,
            "min": 1500.0,
            "max": 2800.0
        },
        {
            "current": 1574.153,
            "min": 1500.0,
            "max": 2800.0
        },
        {
            "current": 1954.64,
            "min": 1500.0,
            "max": 2800.0
        },
        {
            "current": 2097.644,
            "min": 1500.0,
            "max": 2800.0
        },
        {
            "current": 1676.09,
            "min": 1500.0,
            "max": 2800.0
        },
        {
            "current": 1678.31,
            "min": 1500.0,
            "max": 2800.0
        },
        {
            "current": 1969.178,
            "min": 1500.0,
            "max": 2800.0
        },
        {
            "current": 2859.404,
            "min": 1500.0,
            "max": 2800.0
        },
        {
            "current": 3571.247,
            "min": 1500.0,
            "max": 2800.0
        },
        {
            "current": 2867.709,
            "min": 1500.0,
            "max": 2800.0
        },
        {
            "current": 2829.745,
            "min": 1500.0,
            "max": 2800.0
        },
        {
            "current": 2003.13,
            "min": 1500.0,
            "max": 2800.0
        },
        {
            "current": 1675.527,
            "min": 1500.0,
            "max": 2800.0
        },
        {
            "current": 2098.8,
            "min": 1500.0,
            "max": 2800.0
        },
        {
            "current": 1674.076,
            "min": 1500.0,
            "max": 2800.0
        },
        {
            "current": 2099.051,
            "min": 1500.0,
            "max": 2800.0
        },
        {
            "current": 1890.845,
            "min": 1500.0,
            "max": 2800.0
        },
        {
            "current": 1673.277,
            "min": 1500.0,
            "max": 2800.0
        },
        {
            "current": 1676.778,
            "min": 1500.0,
            "max": 2800.0
        },
        {
            "current": 3407.722,
            "min": 1500.0,
            "max": 2800.0
        },
        {
            "current": 2170.197,
            "min": 1500.0,
            "max": 2800.0
        },
        {
            "current": 2796.025,
            "min": 1500.0,
            "max": 2800.0
        },
        {
            "current": 1982.921,
            "min": 1500.0,
            "max": 2800.0
        },
        {
            "current": 3724.875,
            "min": 1500.0,
            "max": 2800.0
        },
        {
            "current": 2974.764,
            "min": 1500.0,
            "max": 2800.0
        },
        {
            "current": 2971.014,
            "min": 1500.0,
            "max": 2800.0
        },
        {
            "current": 2973.733,
            "min": 1500.0,
            "max": 2800.0
        },
        {
            "current": 1495.839,
            "min": 1500.0,
            "max": 2800.0
        },
        {
            "current": 1495.482,
            "min": 1500.0,
            "max": 2800.0
        },
        {
            "current": 1499.012,
            "min": 1500.0,
            "max": 2800.0
        },
        {
            "current": 1497.092,
            "min": 1500.0,
            "max": 2800.0
        },
        {
            "current": 1496.489,
            "min": 1500.0,
            "max": 2800.0
        },
        {
            "current": 1498.277,
            "min": 1500.0,
            "max": 2800.0
        },
        {
            "current": 1496.214,
            "min": 1500.0,
            "max": 2800.0
        },
        {
            "current": 1496.898,
            "min": 1500.0,
            "max": 2800.0
        },
        {
            "current": 1496.616,
            "min": 1500.0,
            "max": 2800.0
        },
        {
            "current": 1494.91,
            "min": 1500.0,
            "max": 2800.0
        },
        {
            "current": 1493.64,
            "min": 1500.0,
            "max": 2800.0
        },
        {
            "current": 1496.558,
            "min": 1500.0,
            "max": 2800.0
        },
        {
            "current": 1496.425,
            "min": 1500.0,
            "max": 2800.0
        },
        {
            "current": 1497.56,
            "min": 1500.0,
            "max": 2800.0
        },
        {
            "current": 1497.169,
            "min": 1500.0,
            "max": 2800.0
        },
        {
            "current": 1497.232,
            "min": 1500.0,
            "max": 2800.0
        },
        {
            "current": 1497.616,
            "min": 1500.0,
            "max": 2800.0
        },
        {
            "current": 1496.78,
            "min": 1500.0,
            "max": 2800.0
        },
        {
            "current": 1499.281,
            "min": 1500.0,
            "max": 2800.0
        },
        {
            "current": 1497.329,
            "min": 1500.0,
            "max": 2800.0
        },
        {
            "current": 1495.078,
            "min": 1500.0,
            "max": 2800.0
        },
        {
            "current": 1496.625,
            "min": 1500.0,
            "max": 2800.0
        },
        {
            "current": 1497.724,
            "min": 1500.0,
            "max": 2800.0
        },
        {
            "current": 1497.309,
            "min": 1500.0,
            "max": 2800.0
        },
        {
            "current": 1495.786,
            "min": 1500.0,
            "max": 2800.0
        },
        {
            "current": 1498.09,
            "min": 1500.0,
            "max": 2800.0
        },
        {
            "current": 1498.791,
            "min": 1500.0,
            "max": 2800.0
        },
        {
            "current": 1497.795,
            "min": 1500.0,
            "max": 2800.0
        },
        {
            "current": 1491.813,
            "min": 1500.0,
            "max": 2800.0
        },
        {
            "current": 1499.093,
            "min": 1500.0,
            "max": 2800.0
        },
        {
            "current": 1502.392,
            "min": 1500.0,
            "max": 2800.0
        },
        {
            "current": 1494.312,
            "min": 1500.0,
            "max": 2800.0
        },
        {
            "current": 1494.541,
            "min": 1500.0,
            "max": 2800.0
        },
        {
            "current": 1498.531,
            "min": 1500.0,
            "max": 2800.0
        },
        {
            "current": 1490.859,
            "min": 1500.0,
            "max": 2800.0
        },
        {
            "current": 1496.351,
            "min": 1500.0,
            "max": 2800.0
        },
        {
            "current": 2085.649,
            "min": 1500.0,
            "max": 2800.0
        },
        {
            "current": 2155.9,
            "min": 1500.0,
            "max": 2800.0
        },
        {
            "current": 2173.633,
            "min": 1500.0,
            "max": 2800.0
        },
        {
            "current": 2128.319,
            "min": 1500.0,
            "max": 2800.0
        },
        {
            "current": 1939.343,
            "min": 1500.0,
            "max": 2800.0
        },
        {
            "current": 1577.529,
            "min": 1500.0,
            "max": 2800.0
        },
        {
            "current": 1594.986,
            "min": 1500.0,
            "max": 2800.0
        },
        {
            "current": 1712.545,
            "min": 1500.0,
            "max": 2800.0
        },
        {
            "current": 2849.761,
            "min": 1500.0,
            "max": 2800.0
        },
        {
            "current": 3554.176,
            "min": 1500.0,
            "max": 2800.0
        },
        {
            "current": 2861.548,
            "min": 1500.0,
            "max": 2800.0
        },
        {
            "current": 2852.837,
            "min": 1500.0,
            "max": 2800.0
        },
        {
            "current": 1907.927,
            "min": 1500.0,
            "max": 2800.0
        },
        {
            "current": 1677.221,
            "min": 1500.0,
            "max": 2800.0
        },
        {
            "current": 2104.929,
            "min": 1500.0,
            "max": 2800.0
        },
        {
            "current": 1676.61,
            "min": 1500.0,
            "max": 2800.0
        },
        {
            "current": 2099.19,
            "min": 1500.0,
            "max": 2800.0
        },
        {
            "current": 1679.412,
            "min": 1500.0,
            "max": 2800.0
        },
        {
            "current": 1675.119,
            "min": 1500.0,
            "max": 2800.0
        },
        {
            "current": 1675.321,
            "min": 1500.0,
            "max": 2800.0
        },
        {
            "current": 3574.875,
            "min": 1500.0,
            "max": 2800.0
        },
        {
            "current": 2169.254,
            "min": 1500.0,
            "max": 2800.0
        },
        {
            "current": 2880.84,
            "min": 1500.0,
            "max": 2800.0
        },
        {
            "current": 2075.981,
            "min": 1500.0,
            "max": 2800.0
        },
        {
            "current": 3705.821,
            "min": 1500.0,
            "max": 2800.0
        },
        {
            "current": 2970.827,
            "min": 1500.0,
            "max": 2800.0
        },
        {
            "current": 2975.575,
            "min": 1500.0,
            "max": 2800.0
        },
        {
            "current": 2974.862,
            "min": 1500.0,
            "max": 2800.0
        },
        {
            "current": 1496.648,
            "min": 1500.0,
            "max": 2800.0
        },
        {
            "current": 1496.127,
            "min": 1500.0,
            "max": 2800.0
        },
        {
            "current": 1495.474,
            "min": 1500.0,
            "max": 2800.0
        },
        {
            "current": 1498.476,
            "min": 1500.0,
            "max": 2800.0
        },
        {
            "current": 1496.213,
            "min": 1500.0,
            "max": 2800.0
        },
        {
            "current": 1496.695,
            "min": 1500.0,
            "max": 2800.0
        },
        {
            "current": 1496.287,
            "min": 1500.0,
            "max": 2800.0
        },
        {
            "current": 1496.971,
            "min": 1500.0,
            "max": 2800.0
        },
        {
            "current": 1496.308,
            "min": 1500.0,
            "max": 2800.0
        },
        {
            "current": 1361.801,
            "min": 1500.0,
            "max": 2800.0
        },
        {
            "current": 1361.545,
            "min": 1500.0,
            "max": 2800.0
        },
        {
            "current": 1496.83,
            "min": 1500.0,
            "max": 2800.0
        },
        {
            "current": 1498.917,
            "min": 1500.0,
            "max": 2800.0
        },
        {
            "current": 1495.468,
            "min": 1500.0,
            "max": 2800.0
        },
        {
            "current": 1496.351,
            "min": 1500.0,
            "max": 2800.0
        },
        {
            "current": 1496.124,
            "min": 1500.0,
            "max": 2800.0
        },
        {
            "current": 1484.212,
            "min": 1500.0,
            "max": 2800.0
        },
        {
            "current": 1482.651,
            "min": 1500.0,
            "max": 2800.0
        },
        {
            "current": 1482.452,
            "min": 1500.0,
            "max": 2800.0
        },
        {
            "current": 1495.419,
            "min": 1500.0,
            "max": 2800.0
        },
        {
            "current": 1377.877,
            "min": 1500.0,
            "max": 2800.0
        },
        {
            "current": 1362.746,
            "min": 1500.0,
            "max": 2800.0
        },
        {
            "current": 1365.388,
            "min": 1500.0,
            "max": 2800.0
        },
        {
            "current": 1391.805,
            "min": 1500.0,
            "max": 2800.0
        },
        {
            "current": 1377.475,
            "min": 1500.0,
            "max": 2800.0
        },
        {
            "current": 1491.047,
            "min": 1500.0,
            "max": 2800.0
        },
        {
            "current": 1172.125,
            "min": 1500.0,
            "max": 2800.0
        },
        {
            "current": 1508.591,
            "min": 1500.0,
            "max": 2800.0
        }
    ],
    "disk": {
        "/": {
            "total": 437.88097381591797,
            "used": 116.00968933105469
        }
    },
    "gpu": "NVIDIA A100-SXM4-80GB",
    "gpu_count": 8,
    "gpu_devices": [
        {
            "name": "NVIDIA A100-SXM4-80GB",
            "memory_total": 85899345920
        },
        {
            "name": "NVIDIA A100-SXM4-80GB",
            "memory_total": 85899345920
        },
        {
            "name": "NVIDIA A100-SXM4-80GB",
            "memory_total": 85899345920
        },
        {
            "name": "NVIDIA A100-SXM4-80GB",
            "memory_total": 85899345920
        },
        {
            "name": "NVIDIA A100-SXM4-80GB",
            "memory_total": 85899345920
        },
        {
            "name": "NVIDIA A100-SXM4-80GB",
            "memory_total": 85899345920
        },
        {
            "name": "NVIDIA A100-SXM4-80GB",
            "memory_total": 85899345920
        },
        {
            "name": "NVIDIA A100-SXM4-80GB",
            "memory_total": 85899345920
        }
    ],
    "memory": {
        "total": 1007.7270240783691
    }
}
