{
    "os": "Linux-5.4.0-162-generic-x86_64-with-glibc2.31",
    "python": "3.10.13",
    "heartbeatAt": "2024-01-30T07:39:11.354921",
    "startedAt": "2024-01-30T07:39:10.878471",
    "docker": null,
    "cuda": null,
    "args": [],
    "state": "running",
    "program": "/sailhome/jphilipp/research_projects/scai-tuning/experiments/hh_rlhf/train/train_sft.py",
    "codePathLocal": "train_sft.py",
    "codePath": "experiments/hh_rlhf/train/train_sft.py",
    "git": {
        "remote": "https://github.com/janphilippfranken/scai-tuning.git",
        "commit": "b6446097922d018235e8e924e0e9a0e86c535e56"
    },
    "email": null,
    "root": "/sailhome/jphilipp/research_projects/scai-tuning",
    "host": "cocoflops-hgx-1",
    "username": "jphilipp",
    "executable": "/scr/jphilipp/miniconda3/envs/scai-tuning/bin/python",
    "cpu_count": 64,
    "cpu_count_logical": 128,
    "cpu_freq": {
        "current": 2021.893406250001,
        "min": 1500.0,
        "max": 2800.0
    },
    "cpu_freq_per_core": [
        {
            "current": 1498.739,
            "min": 1500.0,
            "max": 2800.0
        },
        {
            "current": 1346.296,
            "min": 1500.0,
            "max": 2800.0
        },
        {
            "current": 1338.591,
            "min": 1500.0,
            "max": 2800.0
        },
        {
            "current": 1492.948,
            "min": 1500.0,
            "max": 2800.0
        },
        {
            "current": 1384.117,
            "min": 1500.0,
            "max": 2800.0
        },
        {
            "current": 1386.942,
            "min": 1500.0,
            "max": 2800.0
        },
        {
            "current": 1385.527,
            "min": 1500.0,
            "max": 2800.0
        },
        {
            "current": 1383.879,
            "min": 1500.0,
            "max": 2800.0
        },
        {
            "current": 1358.557,
            "min": 1500.0,
            "max": 2800.0
        },
        {
            "current": 1292.592,
            "min": 1500.0,
            "max": 2800.0
        },
        {
            "current": 1497.741,
            "min": 1500.0,
            "max": 2800.0
        },
        {
            "current": 1497.403,
            "min": 1500.0,
            "max": 2800.0
        },
        {
            "current": 1497.777,
            "min": 1500.0,
            "max": 2800.0
        },
        {
            "current": 1498.713,
            "min": 1500.0,
            "max": 2800.0
        },
        {
            "current": 1498.341,
            "min": 1500.0,
            "max": 2800.0
        },
        {
            "current": 1497.591,
            "min": 1500.0,
            "max": 2800.0
        },
        {
            "current": 1488.268,
            "min": 1500.0,
            "max": 2800.0
        },
        {
            "current": 1463.123,
            "min": 1500.0,
            "max": 2800.0
        },
        {
            "current": 1498.127,
            "min": 1500.0,
            "max": 2800.0
        },
        {
            "current": 1499.349,
            "min": 1500.0,
            "max": 2800.0
        },
        {
            "current": 2759.568,
            "min": 1500.0,
            "max": 2800.0
        },
        {
            "current": 3471.015,
            "min": 1500.0,
            "max": 2800.0
        },
        {
            "current": 2649.156,
            "min": 1500.0,
            "max": 2800.0
        },
        {
            "current": 2457.358,
            "min": 1500.0,
            "max": 2800.0
        },
        {
            "current": 1485.643,
            "min": 1500.0,
            "max": 2800.0
        },
        {
            "current": 1474.462,
            "min": 1500.0,
            "max": 2800.0
        },
        {
            "current": 1495.655,
            "min": 1500.0,
            "max": 2800.0
        },
        {
            "current": 1496.993,
            "min": 1500.0,
            "max": 2800.0
        },
        {
            "current": 2099.406,
            "min": 1500.0,
            "max": 2800.0
        },
        {
            "current": 1677.865,
            "min": 1500.0,
            "max": 2800.0
        },
        {
            "current": 1674.348,
            "min": 1500.0,
            "max": 2800.0
        },
        {
            "current": 1674.918,
            "min": 1500.0,
            "max": 2800.0
        },
        {
            "current": 2799.586,
            "min": 1500.0,
            "max": 2800.0
        },
        {
            "current": 2836.507,
            "min": 1500.0,
            "max": 2800.0
        },
        {
            "current": 3483.812,
            "min": 1500.0,
            "max": 2800.0
        },
        {
            "current": 2793.512,
            "min": 1500.0,
            "max": 2800.0
        },
        {
            "current": 2780.485,
            "min": 1500.0,
            "max": 2800.0
        },
        {
            "current": 3491.868,
            "min": 1500.0,
            "max": 2800.0
        },
        {
            "current": 2786.834,
            "min": 1500.0,
            "max": 2800.0
        },
        {
            "current": 3379.473,
            "min": 1500.0,
            "max": 2800.0
        },
        {
            "current": 3493.275,
            "min": 1500.0,
            "max": 2800.0
        },
        {
            "current": 2789.45,
            "min": 1500.0,
            "max": 2800.0
        },
        {
            "current": 3492.889,
            "min": 1500.0,
            "max": 2800.0
        },
        {
            "current": 3492.952,
            "min": 1500.0,
            "max": 2800.0
        },
        {
            "current": 3492.947,
            "min": 1500.0,
            "max": 2800.0
        },
        {
            "current": 3493.113,
            "min": 1500.0,
            "max": 2800.0
        },
        {
            "current": 3492.999,
            "min": 1500.0,
            "max": 2800.0
        },
        {
            "current": 3488.381,
            "min": 1500.0,
            "max": 2800.0
        },
        {
            "current": 2794.089,
            "min": 1500.0,
            "max": 2800.0
        },
        {
            "current": 3493.271,
            "min": 1500.0,
            "max": 2800.0
        },
        {
            "current": 3496.85,
            "min": 1500.0,
            "max": 2800.0
        },
        {
            "current": 2787.12,
            "min": 1500.0,
            "max": 2800.0
        },
        {
            "current": 1499.094,
            "min": 1500.0,
            "max": 2800.0
        },
        {
            "current": 1497.405,
            "min": 1500.0,
            "max": 2800.0
        },
        {
            "current": 1495.98,
            "min": 1500.0,
            "max": 2800.0
        },
        {
            "current": 1497.212,
            "min": 1500.0,
            "max": 2800.0
        },
        {
            "current": 1498.386,
            "min": 1500.0,
            "max": 2800.0
        },
        {
            "current": 1497.296,
            "min": 1500.0,
            "max": 2800.0
        },
        {
            "current": 1496.856,
            "min": 1500.0,
            "max": 2800.0
        },
        {
            "current": 1497.753,
            "min": 1500.0,
            "max": 2800.0
        },
        {
            "current": 1496.923,
            "min": 1500.0,
            "max": 2800.0
        },
        {
            "current": 1491.243,
            "min": 1500.0,
            "max": 2800.0
        },
        {
            "current": 1495.536,
            "min": 1500.0,
            "max": 2800.0
        },
        {
            "current": 1496.902,
            "min": 1500.0,
            "max": 2800.0
        },
        {
            "current": 1498.837,
            "min": 1500.0,
            "max": 2800.0
        },
        {
            "current": 1499.555,
            "min": 1500.0,
            "max": 2800.0
        },
        {
            "current": 1497.28,
            "min": 1500.0,
            "max": 2800.0
        },
        {
            "current": 1496.512,
            "min": 1500.0,
            "max": 2800.0
        },
        {
            "current": 1499.306,
            "min": 1500.0,
            "max": 2800.0
        },
        {
            "current": 1491.788,
            "min": 1500.0,
            "max": 2800.0
        },
        {
            "current": 1499.454,
            "min": 1500.0,
            "max": 2800.0
        },
        {
            "current": 1491.035,
            "min": 1500.0,
            "max": 2800.0
        },
        {
            "current": 1495.82,
            "min": 1500.0,
            "max": 2800.0
        },
        {
            "current": 1493.156,
            "min": 1500.0,
            "max": 2800.0
        },
        {
            "current": 1468.503,
            "min": 1500.0,
            "max": 2800.0
        },
        {
            "current": 1499.338,
            "min": 1500.0,
            "max": 2800.0
        },
        {
            "current": 1499.173,
            "min": 1500.0,
            "max": 2800.0
        },
        {
            "current": 1494.004,
            "min": 1500.0,
            "max": 2800.0
        },
        {
            "current": 1480.877,
            "min": 1500.0,
            "max": 2800.0
        },
        {
            "current": 1476.597,
            "min": 1500.0,
            "max": 2800.0
        },
        {
            "current": 1475.625,
            "min": 1500.0,
            "max": 2800.0
        },
        {
            "current": 1480.761,
            "min": 1500.0,
            "max": 2800.0
        },
        {
            "current": 1499.251,
            "min": 1500.0,
            "max": 2800.0
        },
        {
            "current": 1499.468,
            "min": 1500.0,
            "max": 2800.0
        },
        {
            "current": 2402.741,
            "min": 1500.0,
            "max": 2800.0
        },
        {
            "current": 3624.88,
            "min": 1500.0,
            "max": 2800.0
        },
        {
            "current": 2478.273,
            "min": 1500.0,
            "max": 2800.0
        },
        {
            "current": 2719.732,
            "min": 1500.0,
            "max": 2800.0
        },
        {
            "current": 1467.971,
            "min": 1500.0,
            "max": 2800.0
        },
        {
            "current": 1474.951,
            "min": 1500.0,
            "max": 2800.0
        },
        {
            "current": 1491.879,
            "min": 1500.0,
            "max": 2800.0
        },
        {
            "current": 1493.423,
            "min": 1500.0,
            "max": 2800.0
        },
        {
            "current": 2079.118,
            "min": 1500.0,
            "max": 2800.0
        },
        {
            "current": 1670.504,
            "min": 1500.0,
            "max": 2800.0
        },
        {
            "current": 1677.104,
            "min": 1500.0,
            "max": 2800.0
        },
        {
            "current": 1677.63,
            "min": 1500.0,
            "max": 2800.0
        },
        {
            "current": 2798.602,
            "min": 1500.0,
            "max": 2800.0
        },
        {
            "current": 2804.538,
            "min": 1500.0,
            "max": 2800.0
        },
        {
            "current": 3499.619,
            "min": 1500.0,
            "max": 2800.0
        },
        {
            "current": 2798.925,
            "min": 1500.0,
            "max": 2800.0
        },
        {
            "current": 2799.457,
            "min": 1500.0,
            "max": 2800.0
        },
        {
            "current": 3499.143,
            "min": 1500.0,
            "max": 2800.0
        },
        {
            "current": 2780.778,
            "min": 1500.0,
            "max": 2800.0
        },
        {
            "current": 3340.381,
            "min": 1500.0,
            "max": 2800.0
        },
        {
            "current": 3499.61,
            "min": 1500.0,
            "max": 2800.0
        },
        {
            "current": 2780.183,
            "min": 1500.0,
            "max": 2800.0
        },
        {
            "current": 3498.569,
            "min": 1500.0,
            "max": 2800.0
        },
        {
            "current": 3488.713,
            "min": 1500.0,
            "max": 2800.0
        },
        {
            "current": 3499.668,
            "min": 1500.0,
            "max": 2800.0
        },
        {
            "current": 3498.318,
            "min": 1500.0,
            "max": 2800.0
        },
        {
            "current": 3493.712,
            "min": 1500.0,
            "max": 2800.0
        },
        {
            "current": 3493.69,
            "min": 1500.0,
            "max": 2800.0
        },
        {
            "current": 2795.588,
            "min": 1500.0,
            "max": 2800.0
        },
        {
            "current": 3496.188,
            "min": 1500.0,
            "max": 2800.0
        },
        {
            "current": 3493.823,
            "min": 1500.0,
            "max": 2800.0
        },
        {
            "current": 2784.68,
            "min": 1500.0,
            "max": 2800.0
        },
        {
            "current": 1496.667,
            "min": 1500.0,
            "max": 2800.0
        },
        {
            "current": 1497.286,
            "min": 1500.0,
            "max": 2800.0
        },
        {
            "current": 1497.522,
            "min": 1500.0,
            "max": 2800.0
        },
        {
            "current": 1497.737,
            "min": 1500.0,
            "max": 2800.0
        },
        {
            "current": 1497.747,
            "min": 1500.0,
            "max": 2800.0
        },
        {
            "current": 1496.821,
            "min": 1500.0,
            "max": 2800.0
        },
        {
            "current": 1496.407,
            "min": 1500.0,
            "max": 2800.0
        },
        {
            "current": 1496.967,
            "min": 1500.0,
            "max": 2800.0
        },
        {
            "current": 1497.556,
            "min": 1500.0,
            "max": 2800.0
        },
        {
            "current": 1492.78,
            "min": 1500.0,
            "max": 2800.0
        },
        {
            "current": 1495.875,
            "min": 1500.0,
            "max": 2800.0
        },
        {
            "current": 1499.024,
            "min": 1500.0,
            "max": 2800.0
        }
    ],
    "disk": {
        "/": {
            "total": 437.88097381591797,
            "used": 147.27349090576172
        }
    },
    "gpu": "NVIDIA A100-SXM4-80GB",
    "gpu_count": 4,
    "gpu_devices": [
        {
            "name": "NVIDIA A100-SXM4-80GB",
            "memory_total": 85899345920
        },
        {
            "name": "NVIDIA A100-SXM4-80GB",
            "memory_total": 85899345920
        },
        {
            "name": "NVIDIA A100-SXM4-80GB",
            "memory_total": 85899345920
        },
        {
            "name": "NVIDIA A100-SXM4-80GB",
            "memory_total": 85899345920
        }
    ],
    "memory": {
        "total": 1007.7270240783691
    }
}
